django_cos_storage/__init__.py
django_cos_storage/file.py
django_cos_storage/storage.py
tencentcloud_django_cos_storage-1.0.0.dist-info/LICENSE
tencentcloud_django_cos_storage-1.0.0.dist-info/METADATA
tencentcloud_django_cos_storage-1.0.0.dist-info/WHEEL
tencentcloud_django_cos_storage-1.0.0.dist-info/RECORD
