Metadata-Version: 2.1
Name: tencentcloud-django-cos-storage
Version: 1.0.0
Summary: A django app for Tencent Cloud Object Storage. 腾讯云对象存储（COS）服务 for Django。
Home-page: https://github.com/Huberyxiao/django-cos-storage
License: BSD-3-Clause
Keywords: django
Author: huberyxxiao
Author-email: huberyxxiao@tencent.com
Requires-Python: >=3.7,<4.0
Classifier: License :: OSI Approved :: BSD License
Classifier: Programming Language :: Python :: 3
Classifier: Programming Language :: Python :: 3.7
Classifier: Programming Language :: Python :: 3.8
Classifier: Programming Language :: Python :: 3.9
Classifier: Programming Language :: Python :: 3.10
Classifier: Programming Language :: Python :: 3.11
Requires-Dist: cos-python-sdk-v5 (>=1.9.4,<2.0.0)
Project-URL: Repository, https://github.com/Huberyxiao/django-cos-storage
